setup.py
bai_indexer/__init__.py
bai_indexer.egg-info/PKG-INFO
bai_indexer.egg-info/SOURCES.txt
bai_indexer.egg-info/dependency_links.txt
bai_indexer.egg-info/entry_points.txt
bai_indexer.egg-info/top_level.txt