Metadata-Version: 1.1
Name: bai-indexer
Version: 0.1.1
Summary: An index for your BAM Index (BAI)
Home-page: https://github.com/danvk/bai-indexer/
Author: Dan Vanderkam
Author-email: danvdk@gmail.com
License: UNKNOWN
Platform: UNKNOWN
Classifier: Environment :: Console
Classifier: Development Status :: 4 - Beta
Classifier: Intended Audience :: Healthcare Industry
Classifier: Intended Audience :: Information Technology
Classifier: License :: OSI Approved :: Apache Software License
Classifier: Topic :: Scientific/Engineering :: Bio-Informatics
